[
    {
        "text": "SCHOOLOF",
        "bbox": [
            [
                6386,
                116
            ],
            [
                6615,
                116
            ],
            [
                6615,
                172
            ],
            [
                6386,
                172
            ]
        ]
    },
    {
        "text": "DESIGN",
        "bbox": [
            [
                6392,
                175
            ],
            [
                6540,
                175
            ],
            [
                6540,
                218
            ],
            [
                6392,
                218
            ]
        ]
    },
    {
        "text": "A1辅助设计工作流",
        "bbox": [
            [
                2731,
                169
            ],
            [
                3427,
                169
            ],
            [
                3427,
                282
            ],
            [
                2731,
                282
            ]
        ]
    },
    {
        "text": "创新创意设计学院",
        "bbox": [
            [
                6385,
                215
            ],
            [
                6673,
                215
            ],
            [
                6673,
                278
            ],
            [
                6385,
                278
            ]
        ]
    },
    {
        "text": "NANI",
        "bbox": [
            [
                155,
                139
            ],
            [
                1469,
                139
            ],
            [
                1469,
                554
            ],
            [
                155,
                554
            ]
        ]
    },
    {
        "text": "指导教师:  万芳",
        "bbox": [
            [
                1826,
                437
            ],
            [
                2113,
                437
            ],
            [
                2113,
                493
            ],
            [
                1826,
                493
            ]
        ]
    },
    {
        "text": "关键词提取",
        "bbox": [
            [
                2812,
                471
            ],
            [
                3152,
                471
            ],
            [
                3152,
                559
            ],
            [
                2812,
                559
            ]
        ]
    },
    {
        "text": "肛造型发散",
        "bbox": [
            [
                4410,
                482
            ],
            [
                4756,
                482
            ],
            [
                4756,
                569
            ],
            [
                4410,
                569
            ]
        ]
    },
    {
        "text": "Midjourney",
        "bbox": [
            [
                4878,
                513
            ],
            [
                5003,
                513
            ],
            [
                5003,
                538
            ],
            [
                4878,
                538
            ]
        ]
    },
    {
        "text": "团队成员:  范玉湘 |黄可心 |张汐",
        "bbox": [
            [
                1825,
                536
            ],
            [
                2413,
                536
            ],
            [
                2413,
                599
            ],
            [
                1825,
                599
            ]
        ]
    },
    {
        "text": "@Miniature Insect Inspired Robot 迷你仿生昆虫机器人",
        "bbox": [
            [
                3242,
                591
            ],
            [
                4085,
                591
            ],
            [
                4085,
                628
            ],
            [
                3242,
                628
            ]
        ]
    },
    {
        "text": "关毽词: Miniature Inspired Robot。",
        "bbox": [
            [
                6050,
                591
            ],
            [
                6569,
                591
            ],
            [
                6569,
                634
            ],
            [
                6050,
                634
            ]
        ]
    },
    {
        "text": "@Metallic Finish 金属质感",
        "bbox": [
            [
                3242,
                638
            ],
            [
                3663,
                638
            ],
            [
                3663,
                681
            ],
            [
                3242,
                681
            ]
        ]
    },
    {
        "text": "Metallic Finish; Camera and UV Light;",
        "bbox": [
            [
                6050,
                638
            ],
            [
                6623,
                638
            ],
            [
                6623,
                681
            ],
            [
                6050,
                681
            ]
        ]
    },
    {
        "text": "家用驱虫加器人",
        "bbox": [
            [
                163,
                583
            ],
            [
                1619,
                583
            ],
            [
                1619,
                841
            ],
            [
                163,
                841
            ]
        ]
    },
    {
        "text": "基于设计概念 我们采用了 回Cameraand UU Light - 摄像头和紫外线灯",
        "bbox": [
            [
                2719,
                662
            ],
            [
                3894,
                662
            ],
            [
                3894,
                725
            ],
            [
                2719,
                725
            ]
        ]
    },
    {
        "text": "我们采用了 Midjourney作为A1辅助",
        "bbox": [
            [
                4417,
                654
            ],
            [
                5045,
                654
            ],
            [
                5045,
                730
            ],
            [
                4417,
                730
            ]
        ]
    },
    {
        "text": "Moth Attracting Light; Electric",
        "bbox": [
            [
                6050,
                691
            ],
            [
                6519,
                691
            ],
            [
                6519,
                734
            ],
            [
                6050,
                734
            ]
        ]
    },
    {
        "text": "AItDesign的工作流进行设",
        "bbox": [
            [
                2719,
                736
            ],
            [
                3207,
                736
            ],
            [
                3207,
                804
            ],
            [
                2719,
                804
            ]
        ]
    },
    {
        "text": "@Moth Attracting Light 吸引飞蛾的强力光源",
        "bbox": [
            [
                3247,
                738
            ],
            [
                3937,
                738
            ],
            [
                3937,
                776
            ],
            [
                3247,
                776
            ]
        ]
    },
    {
        "text": "设计的工具 将提取到的关键词输",
        "bbox": [
            [
                4419,
                732
            ],
            [
                5026,
                732
            ],
            [
                5026,
                787
            ],
            [
                4419,
                787
            ]
        ]
    },
    {
        "text": "Mosquito Zapper, Insecticide Storage;",
        "bbox": [
            [
                6050,
                738
            ],
            [
                6619,
                738
            ],
            [
                6619,
                781
            ],
            [
                6050,
                781
            ]
        ]
    },
    {
        "text": "QElectric Mosquito Zapper 电击蚊蝇",
        "bbox": [
            [
                3242,
                785
            ],
            [
                3821,
                785
            ],
            [
                3821,
                828
            ],
            [
                3242,
                828
            ]
        ]
    },
    {
        "text": "Futuristic Design, Compact and",
        "bbox": [
            [
                6050,
                785
            ],
            [
                6529,
                785
            ],
            [
                6529,
                828
            ],
            [
                6050,
                828
            ]
        ]
    },
    {
        "text": "计 我们首先将设计概念凝 @Insecticide Storage 存储杀虫药",
        "bbox": [
            [
                2720,
                811
            ],
            [
                3763,
                811
            ],
            [
                3763,
                866
            ],
            [
                2720,
                866
            ]
        ]
    },
    {
        "text": "入给MJ并进行多次调试; 选取了15",
        "bbox": [
            [
                4424,
                805
            ],
            [
                5047,
                805
            ],
            [
                5047,
                861
            ],
            [
                4424,
                861
            ]
        ]
    },
    {
        "text": "Effcient; Robotic Pest Control sleek",
        "bbox": [
            [
                6050,
                833
            ],
            [
                6608,
                833
            ],
            [
                6608,
                870
            ],
            [
                6050,
                870
            ]
        ]
    },
    {
        "text": "Dmestic insect repellent rohnt",
        "bbox": [
            [
                252,
                834
            ],
            [
                1642,
                834
            ],
            [
                1642,
                963
            ],
            [
                252,
                963
            ]
        ]
    },
    {
        "text": "练成几个关键词",
        "bbox": [
            [
                2720,
                884
            ],
            [
                3012,
                884
            ],
            [
                3012,
                940
            ],
            [
                2720,
                940
            ]
        ]
    },
    {
        "text": "(JFuturistic Design 未来感设计",
        "bbox": [
            [
                3242,
                880
            ],
            [
                3731,
                880
            ],
            [
                3731,
                923
            ],
            [
                3242,
                923
            ]
        ]
    },
    {
        "text": "张高质量图片",
        "bbox": [
            [
                4418,
                873
            ],
            [
                4675,
                873
            ],
            [
                4675,
                935
            ],
            [
                4418,
                935
            ]
        ]
    },
    {
        "text": "and minimalistic design, photoreal",
        "bbox": [
            [
                6049,
                878
            ],
            [
                6578,
                878
            ],
            [
                6578,
                927
            ],
            [
                6049,
                927
            ]
        ]
    },
    {
        "text": "@Compact and Effcient - 体型小巧高效",
        "bbox": [
            [
                3239,
                923
            ],
            [
                3842,
                923
            ],
            [
                3842,
                975
            ],
            [
                3239,
                975
            ]
        ]
    },
    {
        "text": "details industrial design 一5 250",
        "bbox": [
            [
                6050,
                927
            ],
            [
                6535,
                927
            ],
            [
                6535,
                970
            ],
            [
                6050,
                970
            ]
        ]
    },
    {
        "text": "@Robotic Pest ontrol - 机器人害虫控制",
        "bbox": [
            [
                3242,
                975
            ],
            [
                3858,
                975
            ],
            [
                3858,
                1018
            ],
            [
                3242,
                1018
            ]
        ]
    },
    {
        "text": "背景调研",
        "bbox": [
            [
                195,
                1057
            ],
            [
                551,
                1057
            ],
            [
                551,
                1177
            ],
            [
                195,
                1177
            ]
        ]
    },
    {
        "text": "广东省2024年4月下半月",
        "bbox": [
            [
                206,
                1300
            ],
            [
                661,
                1300
            ],
            [
                661,
                1355
            ],
            [
                206,
                1355
            ]
        ]
    },
    {
        "text": "成蚊密度M01高密度监测点所在地区",
        "bbox": [
            [
                206,
                1347
            ],
            [
                856,
                1347
            ],
            [
                856,
                1402
            ],
            [
                206,
                1402
            ]
        ]
    },
    {
        "text": "STEP",
        "bbox": [
            [
                3994,
                1406
            ],
            [
                4105,
                1406
            ],
            [
                4105,
                1449
            ],
            [
                3994,
                1449
            ]
        ]
    },
    {
        "text": "图片标注",
        "bbox": [
            [
                3987,
                1458
            ],
            [
                4158,
                1458
            ],
            [
                4158,
                1513
            ],
            [
                3987,
                1513
            ]
        ]
    },
    {
        "text": "lora模型训练",
        "bbox": [
            [
                3982,
                1515
            ],
            [
                4232,
                1515
            ],
            [
                4232,
                1571
            ],
            [
                3982,
                1571
            ]
        ]
    },
    {
        "text": "STEP 2",
        "bbox": [
            [
                3999,
                1669
            ],
            [
                4136,
                1669
            ],
            [
                4136,
                1712
            ],
            [
                3999,
                1712
            ]
        ]
    },
    {
        "text": "肛辅助确定最终效果图",
        "bbox": [
            [
                4452,
                1612
            ],
            [
                5108,
                1612
            ],
            [
                5108,
                1705
            ],
            [
                4452,
                1705
            ]
        ]
    },
    {
        "text": "设计草图绘制",
        "bbox": [
            [
                5404,
                1618
            ],
            [
                5813,
                1618
            ],
            [
                5813,
                1711
            ],
            [
                5404,
                1711
            ]
        ]
    },
    {
        "text": "手绘草图上传",
        "bbox": [
            [
                3997,
                1714
            ],
            [
                4244,
                1714
            ],
            [
                4244,
                1777
            ],
            [
                3997,
                1777
            ]
        ]
    },
    {
        "text": " Slable UiffU:",
        "bbox": [
            [
                4841,
                1775
            ],
            [
                4973,
                1775
            ],
            [
                4969,
                1800
            ],
            [
                4841,
                1800
            ]
        ]
    },
    {
        "text": "Controlnet绑定",
        "bbox": [
            [
                3998,
                1784
            ],
            [
                4290,
                1784
            ],
            [
                4290,
                1834
            ],
            [
                3998,
                1834
            ]
        ]
    },
    {
        "text": "基于这些造型 结合头脑",
        "bbox": [
            [
                5412,
                1772
            ],
            [
                5863,
                1772
            ],
            [
                5863,
                1835
            ],
            [
                5412,
                1835
            ]
        ]
    },
    {
        "text": "Lora参数微调",
        "bbox": [
            [
                3993,
                1836
            ],
            [
                4253,
                1836
            ],
            [
                4253,
                1892
            ],
            [
                3993,
                1892
            ]
        ]
    },
    {
        "text": "我们选取了15张符合设计要求的",
        "bbox": [
            [
                4507,
                1856
            ],
            [
                5080,
                1856
            ],
            [
                5080,
                1919
            ],
            [
                4507,
                1919
            ]
        ]
    },
    {
        "text": "风暴 我们形成了一些设",
        "bbox": [
            [
                5413,
                1852
            ],
            [
                5863,
                1852
            ],
            [
                5863,
                1902
            ],
            [
                5413,
                1902
            ]
        ]
    },
    {
        "text": "图片。借助阿里云的AIGCI具训",
        "bbox": [
            [
                4511,
                1927
            ],
            [
                5098,
                1927
            ],
            [
                5098,
                1999
            ],
            [
                4511,
                1999
            ]
        ]
    },
    {
        "text": "计方案井进行草图推敲。",
        "bbox": [
            [
                5412,
                1914
            ],
            [
                5827,
                1914
            ],
            [
                5827,
                1977
            ],
            [
                5412,
                1977
            ]
        ]
    },
    {
        "text": "STEP3",
        "bbox": [
            [
                3993,
                1984
            ],
            [
                4132,
                1984
            ],
            [
                4132,
                2034
            ],
            [
                3993,
                2034
            ]
        ]
    },
    {
        "text": "练了一个Lora模型 并用Stable",
        "bbox": [
            [
                4508,
                2005
            ],
            [
                5089,
                2005
            ],
            [
                5089,
                2060
            ],
            [
                4508,
                2060
            ]
        ]
    },
    {
        "text": "Prompt词调整",
        "bbox": [
            [
                3998,
                2047
            ],
            [
                4269,
                2047
            ],
            [
                4269,
                2097
            ],
            [
                3998,
                2097
            ]
        ]
    },
    {
        "text": "不同造型迭代",
        "bbox": [
            [
                3993,
                2099
            ],
            [
                4243,
                2099
            ],
            [
                4243,
                2155
            ],
            [
                3993,
                2155
            ]
        ]
    },
    {
        "text": "Diffusion 生成了最终效果图",
        "bbox": [
            [
                4508,
                2078
            ],
            [
                5026,
                2078
            ],
            [
                5026,
                2134
            ],
            [
                4508,
                2134
            ]
        ]
    },
    {
        "text": "痛点",
        "bbox": [
            [
                1246,
                2314
            ],
            [
                1367,
                2314
            ],
            [
                1367,
                2376
            ],
            [
                1246,
                2376
            ]
        ]
    },
    {
        "text": "南方气候温暖湿润 适合各类蚊虫 甲虫 蟑螂 . 飞蛾",
        "bbox": [
            [
                1421,
                2315
            ],
            [
                2391,
                2315
            ],
            [
                2391,
                2370
            ],
            [
                1421,
                2370
            ]
        ]
    },
    {
        "text": "分析",
        "bbox": [
            [
                1245,
                2387
            ],
            [
                1378,
                2387
            ],
            [
                1378,
                2462
            ],
            [
                1245,
                2462
            ]
        ]
    },
    {
        "text": "蚂蚁 苍蝇等繁殖 许多人深受各种蚊虫困扰。",
        "bbox": [
            [
                1458,
                2389
            ],
            [
                2292,
                2389
            ],
            [
                2292,
                2444
            ],
            [
                1458,
                2444
            ]
        ]
    },
    {
        "text": "功能架构",
        "bbox": [
            [
                2730,
                2477
            ],
            [
                3091,
                2477
            ],
            [
                3091,
                2597
            ],
            [
                2730,
                2597
            ]
        ]
    },
    {
        "text": "为居民提供良好的居住环境 _ 特别考虑了深",
        "bbox": [
            [
                1621,
                2567
            ],
            [
                2386,
                2567
            ],
            [
                2386,
                2623
            ],
            [
                1621,
                2623
            ]
        ]
    },
    {
        "text": "社会",
        "bbox": [
            [
                1250,
                2634
            ],
            [
                1378,
                2634
            ],
            [
                1378,
                2709
            ],
            [
                1250,
                2709
            ]
        ]
    },
    {
        "text": "圳当地社区居民的必要驱虫需求",
        "bbox": [
            [
                1614,
                2645
            ],
            [
                2192,
                2645
            ],
            [
                2192,
                2708
            ],
            [
                1614,
                2708
            ]
        ]
    },
    {
        "text": "10)()12111",
        "bbox": [
            [
                5444,
                2673
            ],
            [
                5594,
                2673
            ],
            [
                5594,
                2723
            ],
            [
                5444,
                2723
            ]
        ]
    },
    {
        "text": "价值",
        "bbox": [
            [
                1250,
                2713
            ],
            [
                1378,
                2713
            ],
            [
                1378,
                2788
            ],
            [
                1250,
                2788
            ]
        ]
    },
    {
        "text": "飞行能力",
        "bbox": [
            [
                3207,
                2728
            ],
            [
                3440,
                2728
            ],
            [
                3440,
                2803
            ],
            [
                3207,
                2803
            ]
        ]
    },
    {
        "text": "驱除多种害虫 从而防止各种蚊虫传播病毒",
        "bbox": [
            [
                1614,
                2761
            ],
            [
                2387,
                2761
            ],
            [
                2387,
                2824
            ],
            [
                1614,
                2824
            ]
        ]
    },
    {
        "text": "带来的疾病",
        "bbox": [
            [
                1620,
                2840
            ],
            [
                1830,
                2840
            ],
            [
                1830,
                2902
            ],
            [
                1620,
                2902
            ]
        ]
    },
    {
        "text": "内置微型电机和陀螺仪。 配合",
        "bbox": [
            [
                3208,
                2837
            ],
            [
                3631,
                2837
            ],
            [
                3631,
                2892
            ],
            [
                3208,
                2892
            ]
        ]
    },
    {
        "text": "翅膀的振动 能够在空间内自",
        "bbox": [
            [
                3210,
                2915
            ],
            [
                3631,
                2915
            ],
            [
                3631,
                2958
            ],
            [
                3210,
                2958
            ]
        ]
    },
    {
        "text": "由飞行和毖停 井保持静音",
        "bbox": [
            [
                3210,
                2989
            ],
            [
                3600,
                2989
            ],
            [
                3600,
                3032
            ],
            [
                3210,
                3032
            ]
        ]
    },
    {
        "text": "视觉系统",
        "bbox": [
            [
                3828,
                2981
            ],
            [
                4076,
                2981
            ],
            [
                4076,
                3061
            ],
            [
                3828,
                3061
            ]
        ]
    },
    {
        "text": "我们的机器人以环境友好 智能决策为设计理念保证有效驱虫的同时, 最大化减少对当地生态环境造成的影",
        "bbox": [
            [
                194,
                3076
            ],
            [
                2234,
                3076
            ],
            [
                2234,
                3144
            ],
            [
                194,
                3144
            ]
        ]
    },
    {
        "text": "概",
        "bbox": [
            [
                2329,
                3086
            ],
            [
                2404,
                3086
            ],
            [
                2404,
                3172
            ],
            [
                2329,
                3172
            ]
        ]
    },
    {
        "text": "装有红外传感器和摄像头, 能够检测周围环境和识别目标害虫",
        "bbox": [
            [
                3836,
                3100
            ],
            [
                4704,
                3100
            ],
            [
                4704,
                3142
            ],
            [
                3836,
                3142
            ]
        ]
    },
    {
        "text": "响 我们设计了一个家用驱虫机器 ^NANO, 从功能上来看  它具有针对不同昆虫而设计的不同驱逐方式。",
        "bbox": [
            [
                181,
                3189
            ],
            [
                2198,
                3189
            ],
            [
                2198,
                3232
            ],
            [
                181,
                3232
            ]
        ]
    },
    {
        "text": "的运动轨迹 内置人工智能算法进行目标检测, 识别不同类",
        "bbox": [
            [
                3836,
                3173
            ],
            [
                4694,
                3173
            ],
            [
                4694,
                3216
            ],
            [
                3836,
                3216
            ]
        ]
    },
    {
        "text": "如吸引飞蛾的高强度光源_ 吸引蚊蝇的紫外线灯和电网 以及消杀蟑螂所用的药水存储存盒。 从造型上来看, 我们预",
        "bbox": [
            [
                179,
                3266
            ],
            [
                2233,
                3266
            ],
            [
                2233,
                3328
            ],
            [
                179,
                3328
            ]
        ]
    },
    {
        "text": "餮",
        "bbox": [
            [
                2330,
                3166
            ],
            [
                2398,
                3166
            ],
            [
                2398,
                3402
            ],
            [
                2330,
                3402
            ]
        ]
    },
    {
        "text": "型的虫类的运动轨迹 井预判害虫位置, 进行驱虫工作。",
        "bbox": [
            [
                3840,
                3235
            ],
            [
                4683,
                3235
            ],
            [
                4683,
                3291
            ],
            [
                3840,
                3291
            ]
        ]
    },
    {
        "text": "期设计一款迷你的。可以飞行的 也可以落地移动的机器人形象。",
        "bbox": [
            [
                925,
                3355
            ],
            [
                2213,
                3355
            ],
            [
                2213,
                3418
            ],
            [
                925,
                3418
            ]
        ]
    },
    {
        "text": "内置A1系统",
        "bbox": [
            [
                4064,
                3444
            ],
            [
                4355,
                3444
            ],
            [
                4355,
                3524
            ],
            [
                4064,
                3524
            ]
        ]
    },
    {
        "text": "人工智能算法对房间迸行建模导航_ 识别虫类常出",
        "bbox": [
            [
                4051,
                3557
            ],
            [
                4762,
                3557
            ],
            [
                4762,
                3600
            ],
            [
                4051,
                3600
            ]
        ]
    },
    {
        "text": "应用场景",
        "bbox": [
            [
                196,
                3551
            ],
            [
                550,
                3551
            ],
            [
                550,
                3664
            ],
            [
                196,
                3664
            ]
        ]
    },
    {
        "text": "没的地方。 配备超声波避障传感器 与视觉识别系",
        "bbox": [
            [
                4051,
                3631
            ],
            [
                4762,
                3631
            ],
            [
                4762,
                3674
            ],
            [
                4051,
                3674
            ]
        ]
    },
    {
        "text": "农",
        "bbox": [
            [
                5137,
                3522
            ],
            [
                5433,
                3522
            ],
            [
                5433,
                3787
            ],
            [
                5137,
                3787
            ]
        ]
    },
    {
        "text": "统相结合 能够在飞行过程中自动避开障碍物, 确",
        "bbox": [
            [
                4045,
                3693
            ],
            [
                4762,
                3693
            ],
            [
                4762,
                3748
            ],
            [
                4045,
                3748
            ]
        ]
    },
    {
        "text": "保安全飞行。",
        "bbox": [
            [
                4051,
                3773
            ],
            [
                4231,
                3773
            ],
            [
                4231,
                3816
            ],
            [
                4051,
                3816
            ]
        ]
    },
    {
        "text": "蚊子",
        "bbox": [
            [
                5154,
                3855
            ],
            [
                5259,
                3855
            ],
            [
                5259,
                3917
            ],
            [
                5154,
                3917
            ]
        ]
    },
    {
        "text": "飞蛾",
        "bbox": [
            [
                5564,
                3855
            ],
            [
                5664,
                3855
            ],
            [
                5664,
                3917
            ],
            [
                5564,
                3917
            ]
        ]
    },
    {
        "text": "鳃金龟",
        "bbox": [
            [
                5917,
                3855
            ],
            [
                6069,
                3855
            ],
            [
                6069,
                3917
            ],
            [
                5917,
                3917
            ]
        ]
    },
    {
        "text": "美洲大蠊",
        "bbox": [
            [
                6274,
                3855
            ],
            [
                6474,
                3855
            ],
            [
                6474,
                3917
            ],
            [
                6274,
                3917
            ]
        ]
    },
    {
        "text": "投药导管及落地装置",
        "bbox": [
            [
                4054,
                3964
            ],
            [
                4576,
                3964
            ],
            [
                4576,
                4045
            ],
            [
                4054,
                4045
            ]
        ]
    },
    {
        "text": "NANO 飞到蚊子喜爱的",
        "bbox": [
            [
                5055,
                3972
            ],
            [
                5384,
                3972
            ],
            [
                5384,
                4022
            ],
            [
                5055,
                4022
            ]
        ]
    },
    {
        "text": "NANO释放光源 将飞",
        "bbox": [
            [
                5440,
                3978
            ],
            [
                5772,
                3978
            ],
            [
                5772,
                4015
            ],
            [
                5440,
                4015
            ]
        ]
    },
    {
        "text": "NAN0靠近甲虫 通过 NANO通过识别房间中",
        "bbox": [
            [
                5824,
                3967
            ],
            [
                6535,
                3967
            ],
            [
                6535,
                4010
            ],
            [
                5824,
                4010
            ]
        ]
    },
    {
        "text": "环境, 守株待兔 散发",
        "bbox": [
            [
                5056,
                4046
            ],
            [
                5384,
                4046
            ],
            [
                5384,
                4089
            ],
            [
                5056,
                4089
            ]
        ]
    },
    {
        "text": "蛾吸引走到室外",
        "bbox": [
            [
                5439,
                4040
            ],
            [
                5678,
                4040
            ],
            [
                5678,
                4090
            ],
            [
                5439,
                4090
            ]
        ]
    },
    {
        "text": "喷撒药物激发其假死状",
        "bbox": [
            [
                5818,
                4029
            ],
            [
                6157,
                4029
            ],
            [
                6157,
                4085
            ],
            [
                5818,
                4085
            ]
        ]
    },
    {
        "text": "产生的异常细碎响声",
        "bbox": [
            [
                6207,
                4035
            ],
            [
                6504,
                4035
            ],
            [
                6504,
                4085
            ],
            [
                6207,
                4085
            ]
        ]
    },
    {
        "text": "方便陆地活动时作为支撑与行走动力 同时内置导",
        "bbox": [
            [
                4067,
                4078
            ],
            [
                4778,
                4078
            ],
            [
                4778,
                4121
            ],
            [
                4067,
                4121
            ]
        ]
    },
    {
        "text": "紫光灯。 吸引蚊子。靠",
        "bbox": [
            [
                5056,
                4120
            ],
            [
                5383,
                4120
            ],
            [
                5383,
                4163
            ],
            [
                5056,
                4163
            ]
        ]
    },
    {
        "text": "态 通过爪子将其抓起",
        "bbox": [
            [
                5824,
                4115
            ],
            [
                6152,
                4115
            ],
            [
                6152,
                4152
            ],
            [
                5824,
                4152
            ]
        ]
    },
    {
        "text": "识别蟑螂窝位置; 主动",
        "bbox": [
            [
                6208,
                4109
            ],
            [
                6535,
                4109
            ],
            [
                6535,
                4152
            ],
            [
                6208,
                4152
            ]
        ]
    },
    {
        "text": "管 便于导出防治害虫的药物",
        "bbox": [
            [
                4067,
                4151
            ],
            [
                4490,
                4151
            ],
            [
                4490,
                4194
            ],
            [
                4067,
                4194
            ]
        ]
    },
    {
        "text": "近后电击;  或者在飞行",
        "bbox": [
            [
                5054,
                4183
            ],
            [
                5384,
                4183
            ],
            [
                5384,
                4238
            ],
            [
                5054,
                4238
            ]
        ]
    },
    {
        "text": "扔出房间或远处",
        "bbox": [
            [
                5818,
                4177
            ],
            [
                6057,
                4177
            ],
            [
                6057,
                4227
            ],
            [
                5818,
                4227
            ]
        ]
    },
    {
        "text": "投药 井清理残骸",
        "bbox": [
            [
                6202,
                4177
            ],
            [
                6473,
                4177
            ],
            [
                6473,
                4227
            ],
            [
                6202,
                4227
            ]
        ]
    },
    {
        "text": "巡逻模式中击杀",
        "bbox": [
            [
                5056,
                4262
            ],
            [
                5288,
                4262
            ],
            [
                5288,
                4305
            ],
            [
                5056,
                4305
            ]
        ]
    },
    {
        "text": "驱虫装置",
        "bbox": [
            [
                3444,
                4369
            ],
            [
                3682,
                4369
            ],
            [
                3682,
                4444
            ],
            [
                3444,
                4444
            ]
        ]
    },
    {
        "text": "驱虫方案",
        "bbox": [
            [
                5699,
                4337
            ],
            [
                5976,
                4337
            ],
            [
                5976,
                4424
            ],
            [
                5699,
                4424
            ]
        ]
    },
    {
        "text": "户外露营",
        "bbox": [
            [
                394,
                4428
            ],
            [
                630,
                4428
            ],
            [
                630,
                4496
            ],
            [
                394,
                4496
            ]
        ]
    },
    {
        "text": "多人宿舍",
        "bbox": [
            [
                1140,
                4427
            ],
            [
                1378,
                4427
            ],
            [
                1378,
                4502
            ],
            [
                1140,
                4502
            ]
        ]
    },
    {
        "text": "居家使用",
        "bbox": [
            [
                1919,
                4428
            ],
            [
                2145,
                4428
            ],
            [
                2145,
                4496
            ],
            [
                1919,
                4496
            ]
        ]
    },
    {
        "text": "机器人腹部布有一圈紫外灯光 能够有效吸引蛟",
        "bbox": [
            [
                3447,
                4472
            ],
            [
                4126,
                4472
            ],
            [
                4126,
                4515
            ],
            [
                3447,
                4515
            ]
        ]
    },
    {
        "text": "NANO开 启跟随模式 识别人体, 保护其不受蚊虫叮咬",
        "bbox": [
            [
                123,
                4525
            ],
            [
                902,
                4525
            ],
            [
                902,
                4568
            ],
            [
                123,
                4568
            ]
        ]
    },
    {
        "text": "子。苍蝇等害虫靠近 井发出微弱电流击杀",
        "bbox": [
            [
                3451,
                4534
            ],
            [
                4064,
                4534
            ],
            [
                4064,
                4590
            ],
            [
                3451,
                4590
            ]
        ]
    }
]